pypaxtor.py
pypaxtor-0.1.0.dist-info/LICENSE
pypaxtor-0.1.0.dist-info/METADATA
pypaxtor-0.1.0.dist-info/WHEEL
pypaxtor-0.1.0.dist-info/top_level.txt
pypaxtor-0.1.0.dist-info/RECORD
