Metadata-Version: 2.1
Name: pypaxtor
Version: 0.1.0
Summary: Cross-platfom provisioning of home directory storage
Home-page: https://github.com/intuited/pypaxtor
Author: Ted Tibbetts
Author-email: ted@circulated.ca
License: UNKNOWN
Platform: UNKNOWN
Classifier: Programming Language :: Python :: 3
Classifier: License :: OSI Approved :: MIT License
Classifier: Operating System :: OS Independent
License-File: LICENSE
